---
title:  "JVM 공부"
categories:
  - javaStudy
---
# JVM이란 무엇인가?

## 문제상황

### C/C++은 컴파일과 타겟 환경이 각각 다르면 실행이 되지 않는다. 
   - os마다 지원하는 인터페이스나 아키텍처가 다르기 때문이다.
   - 얘네는 크로스 컴파일로 해결시킴 ( 컴파일러가 운영 체제에 맞는 기계어 코드로 변환하여 실행 )
   - 결론은 운영체제마다 따로 컴파일해야 함

### JVM으로 문제 해결!
 - 자바 소스코드는 javaC라는 컴파일러를 거치면 java Byte Code로 변경됨
 - 이 바이트 코드는 JVM이 설치된 환경이라면 어디든 실행가능하다.

<br>

## `WORA(Write Once, Run Anywhere)`
### "한 번 작성하면 어디서나 실행할 수 있다. 단, 그 플랫폼에 맞는 JVM이 설치되어 있어야한다."


<br>

---
### 코드 컴파일 및 실행 과정

#### 모든 컴파일러는 다음과 같은 과정을 겪는다.
`소스코드 → 어휘 분석기 → 구분 분석기 → 의미 분석기 → 중간 코드 생성 → 코드 최적화 → 코드 생성`

#### Compiler Frontend
- `소스코드` 부터 `중간코드 생성`까지
  - 중간코드가 자바 바이트 코드이다.
  - 자바 바이트 코드를 생성하는건? → `Java Compiler(javac)`

#### Compiler Backend
- `중간 코드 생성` 부터 `코드 생성` 까지
- JVM + JIT 컴파일러

### 결론 : 역할을 분리함

<br>

---
# 바이트코드란 무엇인가?

#### 위에서 봤던대로 javac를 거쳐서 생성된 코드이다. → JVM이 실행할 수 있는 중간코드
#### `.class` 파일의 내용으로 인터프리터 또는 JIT 컴파일러로 실행 가능

### SimpleExample.java
```java
public class SimpleExample {
    public static void main(String[] args) {
        int a = 10;
        int b = 20;
        int sum = a + b;
        System.out.println(sum);
    }
}
```

### 실행
```bash
  javac SimpleExample.java
```
- `SimpleExample.class` 파일 생성

### 바이트 코드 확인
```bash
  javap -c SimpleExample.class
```

### 출력

```yaml
Compiled from "SimpleExample.java"
public class SimpleExample {
  public SimpleExample();
    Code:
       0: aload_0
       1: invokespecial
       4: return

  public static void main(java.lang.String[]);
    Code:
       0: bipush        10
       2: istore_1
       3: bipush        20
       5: istore_2
       6: iload_1
       7: iload_2
       8: iadd
       9: istore_3
      10: getstatic   
      13: iload_3
      14: invokevirtual 
      17: return
}
```
이게 뭐임?

### 1. SimpleExample 클래스의 생성자
```yaml
public SimpleExample();
    Code:
       0: aload_0
       1: invokespecial
       4: return
```
- `aload_0`: 현재 객체를 스택에 올림
- `invokespecial`: 부모 클래스의 생성자(super()), private 메서드, 그리고 final 메서드를 호출
- `return`: 생성자 실행 종료

<br>

```yaml
Code:
   0: bipush 10
   2: istore_1
```
- `bipush 10`: 숫자 10을 스택에 올림
- `istore_1`: 스택의 값을 변수 a에 저장 = a(10)을 로컬 변수 1번(index 1)에 저장

<br>

```yaml
  3: bipush 20
  5: istore_2
```
- `bipush 20`: 숫자 20을 스택에 올림
- `istore_2`: 스택의 값을 변수 b에 저장 = b(20)을 지역 변수 2번(index 2)에 저장

<br>

```yaml
  6: iload_1
  7: iload_2
  8: iadd
  9: istore_3
```
- `iload_1`: a 값을 스택에 올림
- `iload_2`: b 값을 스택에 올림
- `iadd`: 스택의 두 값을 더함 (10 + 20 = 30)
- `istore_3`: 결과(30)를 sum에 저장 = 결과(30)를 지역 변수 3번(index 3)에 저장

<br>

```yaml
  10: getstatic
  13: iload_3
  14: invokevirtual
  17: return
```
- `getstatic`: 상수 풀에서 System.out을 찾음
- `iload_3`: sum 값을 스택에 올림
- `invokevirtual`: 상수 풀에서 println(int) 메서드를 찾아서 실행함
- `return`: main() 실행 종료

### Constant Pool
#### 바이트코드에서 필요한 데이터(클래스, 메서드, 변수, 문자열 등)를 저장하는 공간
#### `.class` 파일에 포함되며, JVM이 프로그램 실행 중에 자주 참조해야 하는 정보들을 저장해 둔 공간임

```yaml
Constant pool:
   #1 = Methodref  #4.#10   // java/lang/Object."<init>":()V
   #2 = Fieldref   #11.#12  // java/lang/System.out:Ljava/io/PrintStream;
   #3 = Methodref  #13.#14  // java/io/PrintStream.println:(I)V
   #4 = Class      #15      // java/lang/Object
   #10 = NameAndType #16:#17  // "<init>":()V
```
`#2` 에서 System.out 필드 찾고

`#3` 에서 println(int) 찾음

#### → 바이트코드는 실행 중에 필요한 정보를 직접 저장하지 않고, "상수 풀에서 참조"하는 방식으로 동작함




<br>

---

## JIT 컴파일러란 무엇이며 어떻게 동작하는지

### JVM 구성요소 중에서 Excution Engin에 해당한다. 
 1. #### 인터프리터 방식으로 시작
2. #### 핫스팟(자주 등장하는) 코드를 감지함
3. #### 기계어로 변환후 캐시에 저장해서 이후에는 해석 없이 기계어로 실행
4. #### 초기 실행이 느리지만 반복 실행 속도는 빠르다

<br>

### 컴파일러의 최적화 방식
- `인라이닝` 자주 호출되는 메서드를 메서드 호출 없이 직접 코드에 삽입함
  - `add()`메서드를 인라인 처리하여 호출 없이 바로 10+20을 계산함
  
  <br>
  
- `루프 전개`
  - 반복 횟수를 줄인다.
    
```java
for (int i = 0; i < 1000000; i++) System.out.println(i); 

// 이렇게 되어있다면 아래처럼 부분 전개함
// 완전 전개도 있는데 그건 그냥 반복문을 벗기는거임 (반복 횟수가 비교적 적을때)

for (int i = 0; i < 1000000; i += 4) {
  System.out.println(i);
  System.out.println(i + 1);
  System.out.println(i + 2);
  System.out.println(i + 3);
}
```
  
<br>

-   `데드 코드 제거`
    - 실행되지 않는 코드 삭제

<br>

---

## JVM 구성 요소
### `Class Loader`

 - ### 로딩
   - `.class` 파일(바이트코드)를 동적으로 JVM메모리에 올린다.
 - ### 링크와 초기화
   - 바이트 코드의 무결성을 체크하고 클래스 내부에서 참조하는 메서드, 변수, 클래스 등을 연결한다.

<br>

### `Excution Engin`

- ### 인터프리터(Interpreter)
  - 바이트 코드 한 줄씩 읽고 해석하여 실행한다 → 느림
- ### JIT(Just In Time)
  - 전체 메서드를 기계어(네이티브 코드)로 변환하여 실행
  - 자주 실행되는 코드(핫스팟)를 기계어(네이티브 코드)로 변환하여 실행 속도를 최적화함
    - hot() 메서드가 10만번 실행되면? → 핫스팟으로 감지
    - JIT는 hot() 네이티 코드로 변환해서 최적화함
    - 이후에 바이트코드 대신에 네이티브 코드를 실행해서 속도를 높임
- ### GC(Garbage Collector) - Mark and Sweep 과정
  - 동적으로 할당된 메모리 영역 중에서 더 이상 사용되지 않는 객체를 탐지하여 해제하는 기능
    - 1️⃣ 객체가 힙(Heap) 영역에 생성됨
    -  2️⃣ 객체가 더 이상 참조되지 않으면 GC가 이를 감지
    -  3️⃣ GC가 필요 없는 객체를 제거하고 메모리를 회수
    -  4️⃣ 남아 있는 객체를 최적화하여 메모리 단편화를 줄임 (Compaction)
  - C/C++는 명시적으로 메모리를 해제해줘야함
  - 스택의 영역에 있는 모든 변수를 스캔하면서 어떤 객체를 참조하고 있는지 찾아서 찜꽁한다.(Mark)
  - 그 객체가 참조하고 있는 객체까지 찾아서 마킹(Mark)하고 마킹되지 않은 놈들을 heap에서 제거(Sweep)한다.
 
    
<br>


### `Runtime Data Areas`

#### 자바 프로그램 실행 중 필요한 데이터를 저장하는 메모리 공간

- ### 모든 스레드가 공유하는 메모리 공간
  - #### 메서드 영역
    - 클래스, 메서드, static 변수등 저장 (클래스 로더가 정보를 파싱해서 저장함)
  - #### 힙 영역
    - 힙 영역에는 객체(instance)가 저장 (프로그램을 실행하면서 생성한 객체들 저장)



- ### 스레드별로 따로 존재하는 영역
  - #### PC(Program Counter)
    - 스레드는 메서드를 실행하고 있음
    - PC는 그 메서드 안에서 "CPU가 다음에 실행할 명령어가 어디에 있는지"를 추적하는 역할 (바이트코드 몇번째 줄을 실행할지)
  
    <br><br>

  - #### 네이티브 메서드 스택
    - C/C++ 기계어 실행 공간
    - JVM이 자바 바이트 코드가 아니라 C나 C++ 코드를 컴파일 해서 사용하는 경우가 있음
    - 성능 향상 목적임
    
      <br><br>
    
  - #### 스택 영역
    - 메서드가 호출될 때마다 생성되는 임시 메모리 공간

  ```java
    public class StackExample {
        public static void main(String[] args) {
            methodA();
        }
    
        static void methodA() {
            int a = 10;
            methodB();
        }
    
        static void methodB() {
            int b = 20;
        }
    }
  ```

#### 동작 순서
`` `push` main() → `push` methodA() → `push`methodB() → `pop` methodB() → `pop` methodA() → `pop` main() ``
    
  - 자바 스택은 스레드 별로 1개만 존재
  - 스택 프레임은 메서드가 호출될 때마다 생성됨
  - 메서드 실행이 끝나면 pop되서 제거됨 → 힙 영역에 남은 객체타입의 데이터는 GC가 제거시킴

    
      <br>
    
  - 스택과 스택 프레임의 차이점

| 단계          | 스택(Stack) 상태                     | 스택 프레임(Stack Frame)                 |
|--------------|--------------------------------|--------------------------------|
| push main()  | main() 실행 (최초 스택 프레임 추가)   | main의 실행 정보 (매개변수, 지역 변수 등) |
| push methodA() | methodA() 실행 (새 스택 프레임 추가) | methodA의 실행 정보 저장       |
| push methodB() | methodB() 실행 (새 스택 프레임 추가) | methodB의 실행 정보 저장       |
| pop methodB()  | methodB() 실행 종료 (스택에서 제거)  | methodB의 스택 프레임 삭제     |
| pop methodA()  | methodA() 실행 종료 (스택에서 제거)  | methodA의 스택 프레임 삭제     |
| pop main()    | main() 실행 종료 (스택에서 제거)   | main의 스택 프레임 삭제 (스택이 비워짐) |

    
- 스택 프레임에는 바이트코드가 실행되기 위해 로컬 변수, 상수 풀, 메서드 반환 주소등이 담겨있음

<br>

---

### JDK와 JRE의 차이

#### JDK는 `Java Development Kit` 으로 JRE를 포함한다. 
#### 추가로 컴파일러(javac), 디버거(jdb), Javadoc 등의 개발 도구가 있음 (JRE 설명은 위에 있다.)

- #### JDK = JRE + 개발 도구
- #### JRE는 실행만 가능하지만, JDK는 개발과 실행이 모두 가능함.
- ## JDK를 설치하자!



